searchx/__init__.py
searchx/search.py
searchx/setup.py
shadowsearch/__init__.py
shadowsearch/search.py
shadowsearch/setup.py
shadowsearch-0.0.2.dist-info/METADATA
shadowsearch-0.0.2.dist-info/WHEEL
shadowsearch-0.0.2.dist-info/top_level.txt
shadowsearch-0.0.2.dist-info/RECORD
